{
  "response": {
    "data": [
      {
        "commoditycode": "01010000",
        "commoditydescription": "Live Horses, Asses, Mules"
      },
      {
        "commoditycode": "01020000",
        "commoditydescription": "Live Bovine animals"
      },
      {
        "commoditycode": "01040000",
        "commoditydescription": "Live Sheep and Goats"
      },
      {
        "commoditycode": "03041000",
        "commoditydescription": "Fresh or Chilled"
      },
      {
        "commoditycode": "04022920",
        "commoditydescription": "Milk for Babies"
      },
      {
        "commoditycode": "03049000",
        "commoditydescription": "Other"
      },
      {
        "commoditycode": "01010000",
        "commoditydescription": "Live Horses, Asses, Mules"
      },
      {
        "commoditycode": "01020000",
        "commoditydescription": "Live Bovine animals"
      },
      {
        "commoditycode": "01040000",
        "commoditydescription": "Live Sheep and Goats"
      },
      {
        "commoditycode": "03041000",
        "commoditydescription": "Fresh or Chilled"
      },
      {
        "commoditycode": "04022920",
        "commoditydescription": "Milk for Babies"
      },
      {
        "commoditycode": "03049000",
        "commoditydescription": "Other"
      },
      {
        "commoditycode": "01010000",
        "commoditydescription": "test"
      },
      {
        "commoditycode": "01010000",
        "commoditydescription": "Live Horses, Asses, Mules"
      },
      {
        "commoditycode": "01020000",
        "commoditydescription": "Live Bovine animals"
      },
      {
        "commoditycode": "01040000",
        "commoditydescription": "Live Sheep and Goats"
      },
      {
        "commoditycode": "03041000",
        "commoditydescription": "Fresh or Chilled"
      },
      {
        "commoditycode": "04022920",
        "commoditydescription": "Milk for Babies"
      },
      {
        "commoditycode": "03049000",
        "commoditydescription": "Other"
      },
      {
        "commoditycode": "01010000",
        "commoditydescription": "Live Horses, Asses, Mules"
      },
      {
        "commoditycode": "01020000",
        "commoditydescription": "Live Bovine animals"
      },
      {
        "commoditycode": "01040000",
        "commoditydescription": "Live Sheep and Goats"
      },
      {
        "commoditycode": "03041000",
        "commoditydescription": "Fresh or Chilled"
      },
      {
        "commoditycode": "04022920",
        "commoditydescription": "Milk for Babies"
      },
      {
        "commoditycode": "03049000",
        "commoditydescription": "Other"
      },
      {
        "commoditycode": "01010000",
        "commoditydescription": "test"
      }
    ]
  }
}
